aiotrading/__init__.py
aiotrading/candle.py
aiotrading/order.py
aiotrading/stream.py
aiotrading/trade.py
aiotrading/exchange/__init__.py
aiotrading/exchange/binance_futures.py
aiotrading/exchange/exchange.py
aiotrading/exchanges/__init__.py
aiotrading/exchanges/binance/__init__.py
aiotrading/exchanges/binance/binance_futures.py
aiotrading/exchanges/binance/candle_stream.py
aiotrading/exchanges/binance/market_stream.py
aiotrading/exchanges/binance/order_update_stream.py
aiotrading/exchanges/binance/trade_stream.py
aiotrading/exchanges/binance/user_stream.py
aiotrading/types/__init__.py
aiotrading/types/candle.py
aiotrading/types/order.py
aiotrading/types/order_update.py
aiotrading/types/trade.py
aiotrading-0.0.4.dist-info/LICENSE
aiotrading-0.0.4.dist-info/METADATA
aiotrading-0.0.4.dist-info/WHEEL
aiotrading-0.0.4.dist-info/top_level.txt
aiotrading-0.0.4.dist-info/RECORD
