Metadata-Version: 2.1
Name: aiotrading
Version: 0.0.4
Summary: Async trading library based on asyncio
Home-page: https://github.com/fadishei/aiotrading
Author: Hamid Fadishei
Author-email: fadishei@yahoo.com
License: GPLv3+
Keywords: trading asyncio binance restful websockets
Platform: UNKNOWN
Classifier: Development Status :: 3 - Alpha
Classifier: Intended Audience :: Developers
Classifier: Intended Audience :: Financial and Insurance Industry
Classifier: License :: OSI Approved :: GNU General Public License v3 or later (GPLv3+)
Classifier: Natural Language :: English
Classifier: Operating System :: OS Independent
Classifier: Programming Language :: Python
Classifier: Programming Language :: Python :: 3
Classifier: Topic :: Software Development :: Libraries
Requires-Python: >=3.6
Requires-Dist: websockets (>=8.1)
Requires-Dist: aiohttp (>=3.6.2)
Requires-Dist: aiodns (>=1.1.1)
